{
  "updatedAt": "2026-05-29T22:14:33.597Z",
  "count": 15,
  "games": [
    {
      "game": "San Francisco Giants @ Colorado Rockies",
      "homeTeam": "Colorado Rockies",
      "awayTeam": "San Francisco Giants",
      "chainReactionScore": 80.4,
      "inningExplosionRisk": 73.2,
      "rapidFireHrProbability": 100,
      "pitcherTiltFactor": 49.2,
      "bullpenStressMultiplier": 54.8,
      "stackEscalationScore": 100,
      "comebackVolatility": 67.5,
      "crowdMomentumRating": 85.2,
      "leverageScore": 62.2,
      "hrEnvironmentScore": 20.5,
      "chainReactionLabel": "RAPID FIRE RISK",
      "visualHeatLevel": "ORANGE",
      "liveAlert": "CHAIN REACTION ACTIVE"
    },
    {
      "game": "Atlanta Braves @ Cincinnati Reds",
      "homeTeam": "Cincinnati Reds",
      "awayTeam": "Atlanta Braves",
      "chainReactionScore": 79.1,
      "inningExplosionRisk": 71.3,
      "rapidFireHrProbability": 100,
      "pitcherTiltFactor": 46,
      "bullpenStressMultiplier": 50.9,
      "stackEscalationScore": 100,
      "comebackVolatility": 64.5,
      "crowdMomentumRating": 84.2,
      "leverageScore": 58.4,
      "hrEnvironmentScore": 19.3,
      "chainReactionLabel": "RAPID FIRE RISK",
      "visualHeatLevel": "ORANGE",
      "liveAlert": "CHAIN REACTION ACTIVE"
    },
    {
      "game": "Chicago Cubs @ St. Louis Cardinals",
      "homeTeam": "St. Louis Cardinals",
      "awayTeam": "Chicago Cubs",
      "chainReactionScore": 78.2,
      "inningExplosionRisk": 70,
      "rapidFireHrProbability": 100,
      "pitcherTiltFactor": 43.7,
      "bullpenStressMultiplier": 48.5,
      "stackEscalationScore": 100,
      "comebackVolatility": 62.3,
      "crowdMomentumRating": 83.5,
      "leverageScore": 55.4,
      "hrEnvironmentScore": 18.3,
      "chainReactionLabel": "RAPID FIRE RISK",
      "visualHeatLevel": "ORANGE",
      "liveAlert": "CHAIN REACTION ACTIVE"
    },
    {
      "game": "New York Yankees @ Athletics",
      "homeTeam": "Athletics",
      "awayTeam": "New York Yankees",
      "chainReactionScore": 76.8,
      "inningExplosionRisk": 68.3,
      "rapidFireHrProbability": 100,
      "pitcherTiltFactor": 40.8,
      "bullpenStressMultiplier": 45.3,
      "stackEscalationScore": 98.6,
      "comebackVolatility": 59.4,
      "crowdMomentumRating": 82,
      "leverageScore": 51.6,
      "hrEnvironmentScore": 17,
      "chainReactionLabel": "RAPID FIRE RISK",
      "visualHeatLevel": "ORANGE",
      "liveAlert": "CHAIN REACTION ACTIVE"
    },
    {
      "game": "Detroit Tigers @ Chicago White Sox",
      "homeTeam": "Chicago White Sox",
      "awayTeam": "Detroit Tigers",
      "chainReactionScore": 76.4,
      "inningExplosionRisk": 68.1,
      "rapidFireHrProbability": 100,
      "pitcherTiltFactor": 40.4,
      "bullpenStressMultiplier": 44.8,
      "stackEscalationScore": 97.6,
      "comebackVolatility": 59,
      "crowdMomentumRating": 81.4,
      "leverageScore": 51.1,
      "hrEnvironmentScore": 16.9,
      "chainReactionLabel": "RAPID FIRE RISK",
      "visualHeatLevel": "ORANGE",
      "liveAlert": "CHAIN REACTION ACTIVE"
    },
    {
      "game": "San Diego Padres @ Washington Nationals",
      "homeTeam": "Washington Nationals",
      "awayTeam": "San Diego Padres",
      "chainReactionScore": 76.1,
      "inningExplosionRisk": 67.9,
      "rapidFireHrProbability": 100,
      "pitcherTiltFactor": 39.9,
      "bullpenStressMultiplier": 44.4,
      "stackEscalationScore": 96.6,
      "comebackVolatility": 58.6,
      "crowdMomentumRating": 80.8,
      "leverageScore": 50.5,
      "hrEnvironmentScore": 16.7,
      "chainReactionLabel": "RAPID FIRE RISK",
      "visualHeatLevel": "ORANGE",
      "liveAlert": "CHAIN REACTION ACTIVE"
    },
    {
      "game": "Arizona Diamondbacks @ Seattle Mariners",
      "homeTeam": "Seattle Mariners",
      "awayTeam": "Arizona Diamondbacks",
      "chainReactionScore": 75.9,
      "inningExplosionRisk": 67.7,
      "rapidFireHrProbability": 100,
      "pitcherTiltFactor": 39.7,
      "bullpenStressMultiplier": 44.2,
      "stackEscalationScore": 96.1,
      "comebackVolatility": 58.3,
      "crowdMomentumRating": 80.5,
      "leverageScore": 50.2,
      "hrEnvironmentScore": 16.6,
      "chainReactionLabel": "RAPID FIRE RISK",
      "visualHeatLevel": "ORANGE",
      "liveAlert": "CHAIN REACTION ACTIVE"
    },
    {
      "game": "Toronto Blue Jays @ Baltimore Orioles",
      "homeTeam": "Baltimore Orioles",
      "awayTeam": "Toronto Blue Jays",
      "chainReactionScore": 75.7,
      "inningExplosionRisk": 67.6,
      "rapidFireHrProbability": 100,
      "pitcherTiltFactor": 39.5,
      "bullpenStressMultiplier": 43.9,
      "stackEscalationScore": 95.6,
      "comebackVolatility": 58.1,
      "crowdMomentumRating": 80.2,
      "leverageScore": 49.9,
      "hrEnvironmentScore": 16.5,
      "chainReactionLabel": "RAPID FIRE RISK",
      "visualHeatLevel": "ORANGE",
      "liveAlert": "CHAIN REACTION ACTIVE"
    },
    {
      "game": "Kansas City Royals @ Texas Rangers",
      "homeTeam": "Texas Rangers",
      "awayTeam": "Kansas City Royals",
      "chainReactionScore": 75.3,
      "inningExplosionRisk": 67.3,
      "rapidFireHrProbability": 100,
      "pitcherTiltFactor": 39,
      "bullpenStressMultiplier": 43.4,
      "stackEscalationScore": 94.6,
      "comebackVolatility": 57.7,
      "crowdMomentumRating": 79.6,
      "leverageScore": 49.3,
      "hrEnvironmentScore": 16.3,
      "chainReactionLabel": "RAPID FIRE RISK",
      "visualHeatLevel": "ORANGE",
      "liveAlert": "CHAIN REACTION ACTIVE"
    },
    {
      "game": "Boston Red Sox @ Cleveland Guardians",
      "homeTeam": "Cleveland Guardians",
      "awayTeam": "Boston Red Sox",
      "chainReactionScore": 75.1,
      "inningExplosionRisk": 67.2,
      "rapidFireHrProbability": 100,
      "pitcherTiltFactor": 38.8,
      "bullpenStressMultiplier": 43.1,
      "stackEscalationScore": 94.1,
      "comebackVolatility": 57.4,
      "crowdMomentumRating": 79.3,
      "leverageScore": 49,
      "hrEnvironmentScore": 16.2,
      "chainReactionLabel": "RAPID FIRE RISK",
      "visualHeatLevel": "ORANGE",
      "liveAlert": "CHAIN REACTION ACTIVE"
    },
    {
      "game": "Miami Marlins @ New York Mets",
      "homeTeam": "New York Mets",
      "awayTeam": "Miami Marlins",
      "chainReactionScore": 74.9,
      "inningExplosionRisk": 67.1,
      "rapidFireHrProbability": 100,
      "pitcherTiltFactor": 38.5,
      "bullpenStressMultiplier": 43,
      "stackEscalationScore": 93.6,
      "comebackVolatility": 57.2,
      "crowdMomentumRating": 79,
      "leverageScore": 48.7,
      "hrEnvironmentScore": 16.1,
      "chainReactionLabel": "CHAIN ACTIVE",
      "visualHeatLevel": "YELLOW",
      "liveAlert": "CHAIN REACTION ACTIVE"
    },
    {
      "game": "Los Angeles Angels @ Tampa Bay Rays",
      "homeTeam": "Tampa Bay Rays",
      "awayTeam": "Los Angeles Angels",
      "chainReactionScore": 74.5,
      "inningExplosionRisk": 66.8,
      "rapidFireHrProbability": 100,
      "pitcherTiltFactor": 38.1,
      "bullpenStressMultiplier": 42.5,
      "stackEscalationScore": 92.6,
      "comebackVolatility": 56.8,
      "crowdMomentumRating": 78.4,
      "leverageScore": 48.1,
      "hrEnvironmentScore": 15.9,
      "chainReactionLabel": "CHAIN ACTIVE",
      "visualHeatLevel": "YELLOW",
      "liveAlert": "CHAIN REACTION ACTIVE"
    },
    {
      "game": "Milwaukee Brewers @ Houston Astros",
      "homeTeam": "Houston Astros",
      "awayTeam": "Milwaukee Brewers",
      "chainReactionScore": 73.2,
      "inningExplosionRisk": 65.9,
      "rapidFireHrProbability": 100,
      "pitcherTiltFactor": 36.5,
      "bullpenStressMultiplier": 40.8,
      "stackEscalationScore": 89.2,
      "comebackVolatility": 55.3,
      "crowdMomentumRating": 76.4,
      "leverageScore": 46.1,
      "hrEnvironmentScore": 15.2,
      "chainReactionLabel": "CHAIN ACTIVE",
      "visualHeatLevel": "YELLOW",
      "liveAlert": "CHAIN REACTION ACTIVE"
    },
    {
      "game": "Minnesota Twins @ Pittsburgh Pirates",
      "homeTeam": "Pittsburgh Pirates",
      "awayTeam": "Minnesota Twins",
      "chainReactionScore": 71.7,
      "inningExplosionRisk": 64.9,
      "rapidFireHrProbability": 100,
      "pitcherTiltFactor": 34.7,
      "bullpenStressMultiplier": 38.8,
      "stackEscalationScore": 85.2,
      "comebackVolatility": 53.5,
      "crowdMomentumRating": 74,
      "leverageScore": 43.7,
      "hrEnvironmentScore": 14.4,
      "chainReactionLabel": "CHAIN ACTIVE",
      "visualHeatLevel": "YELLOW",
      "liveAlert": "CHAIN REACTION ACTIVE"
    },
    {
      "game": "Philadelphia Phillies @ Los Angeles Dodgers",
      "homeTeam": "Los Angeles Dodgers",
      "awayTeam": "Philadelphia Phillies",
      "chainReactionScore": 71.7,
      "inningExplosionRisk": 64.9,
      "rapidFireHrProbability": 100,
      "pitcherTiltFactor": 34.7,
      "bullpenStressMultiplier": 38.8,
      "stackEscalationScore": 85.2,
      "comebackVolatility": 53.5,
      "crowdMomentumRating": 74,
      "leverageScore": 43.7,
      "hrEnvironmentScore": 14.4,
      "chainReactionLabel": "CHAIN ACTIVE",
      "visualHeatLevel": "YELLOW",
      "liveAlert": "CHAIN REACTION ACTIVE"
    }
  ]
}